collibra_import/__init__.py
collibra_import/api_client.py
collibra_import/configuration.py
collibra_import/rest.py
collibra_import/api/__init__.py
collibra_import/api/import_api.py
collibra_import/api/import_results_api.py
collibra_import/models/__init__.py
collibra_import/models/any_of_import_json_in_job_request.py
collibra_import/models/asset_identifier.py
collibra_import/models/asset_import_command.py
collibra_import/models/asset_type_identifier.py
collibra_import/models/attribute_value.py
collibra_import/models/batch_csvjob_body.py
collibra_import/models/batch_exceljob_body.py
collibra_import/models/batch_jsonjob_body.py
collibra_import/models/category_reference.py
collibra_import/models/community_identifier.py
collibra_import/models/community_import_command.py
collibra_import/models/complex_relation_identifier.py
collibra_import/models/complex_relation_import_command.py
collibra_import/models/complex_relation_type_identifier.py
collibra_import/models/domain_identifier.py
collibra_import/models/domain_import_command.py
collibra_import/models/domain_type_identifier.py
collibra_import/models/external_identifier.py
collibra_import/models/finalize_job_body.py
collibra_import/models/find_synchronization_request.py
collibra_import/models/import_command_reference.py
collibra_import/models/import_counters.py
collibra_import/models/import_csv_in_job_request.py
collibra_import/models/import_csvjob_body.py
collibra_import/models/import_error.py
collibra_import/models/import_error_paged_response.py
collibra_import/models/import_excel_in_job_request.py
collibra_import/models/import_exceljob_body.py
collibra_import/models/import_json_in_job_request.py
collibra_import/models/import_jsonjob_body.py
collibra_import/models/import_summary.py
collibra_import/models/job.py
collibra_import/models/mapping_identifier.py
collibra_import/models/mapping_import_command.py
collibra_import/models/owner.py
collibra_import/models/paged_response_import_error.py
collibra_import_200-2.0.0.dist-info/METADATA
collibra_import_200-2.0.0.dist-info/WHEEL
collibra_import_200-2.0.0.dist-info/top_level.txt
collibra_import_200-2.0.0.dist-info/RECORD
