Metadata-Version: 2.1
Name: collibra-import-200
Version: 2.0.0
Summary: Collibra Import API
Home-page: 
Author-email: 
Keywords: Swagger,Collibra Import API
Requires-Dist: urllib3 (>=1.15)
Requires-Dist: six (>=1.10)
Requires-Dist: certifi
Requires-Dist: python-dateutil
